mcp_slicer/__init__.py
mcp_slicer/main.py
mcp_slicer/mcp_server.py
mcp_slicer/py.typed
mcp_slicer-0.2.1.dist-info/METADATA
mcp_slicer-0.2.1.dist-info/WHEEL
mcp_slicer-0.2.1.dist-info/entry_points.txt
mcp_slicer-0.2.1.dist-info/RECORD
