Metadata-Version: 2.4
Name: mcp-slicer
Version: 0.2.1
Summary: A MCP server for 3D Slicer
Project-URL: Homepage, https://github.com/zhaoyouj/mcp-slicer
Project-URL: Documentation, https://github.com/zhaoyouj/mcp-slicer#readme
Project-URL: Repository, https://github.com/zhaoyouj/mcp-slicer.git
Project-URL: Bug Tracker, https://github.com/zhaoyouj/mcp-slicer/issues
Author-email: zhaoyouj <zhaoyouj@outlook.com>
License-Expression: MIT
Keywords: 3d slicer,mcp,medical imaging
Classifier: Development Status :: 2 - Pre-Alpha
Classifier: Intended Audience :: Healthcare Industry
Classifier: License :: OSI Approved :: MIT License
Classifier: Operating System :: OS Independent
Classifier: Programming Language :: Python :: 3
Classifier: Programming Language :: Python :: 3.13
Classifier: Topic :: Scientific/Engineering :: Medical Science Apps.
Requires-Python: >=3.13
Requires-Dist: mcp[cli]>=1.4.1
Requires-Dist: requests>=2.32.3
